{
  "formatVersion": 1,
  "database": {
    "version": 8,
    "identityHash": "c77197d0c2a39d8d1595fc3bbf9d8368",
    "entities": [
      {
        "tableName": "apps",
        "createSql": "CREATE TABLE IF NOT EXISTS `${TABLE_NAME}` (`packageName` TEXT NOT NULL, `appName` TEXT NOT NULL, `categoryId` TEXT NOT NULL, `iconUrl` TEXT NOT NULL, `isSystemApp` INTEGER NOT NULL, `isInstalled` INTEGER NOT NULL, `installTime` INTEGER NOT NULL, `lastUpdated` INTEGER NOT NULL, `customNotes` TEXT NOT NULL, `usageCount` INTEGER NOT NULL, `lastUsedTimestamp` INTEGER NOT NULL, `notificationCount` INTEGER NOT NULL, `notificationImportance` INTEGER NOT NULL, `notificationText` TEXT NOT NULL, `appSizeBytes` INTEGER NOT NULL, `isHidden` INTEGER NOT NULL, `firstInstalledTime` INTEGER NOT NULL, `lastUpdatedTime` INTEGER NOT NULL, `targetSdkVersion` INTEGER NOT NULL, `versionName` TEXT NOT NULL, PRIMARY KEY(`packageName`))",
        "fields": [
          {
            "fieldPath": "packageName",
            "columnName": "packageName",
            "affinity": "TEXT",
            "notNull": true
          },
          {
            "fieldPath": "appName",
            "columnName": "appName",
            "affinity": "TEXT",
            "notNull": true
          },
          {
            "fieldPath": "categoryId",
            "columnName": "categoryId",
            "affinity": "TEXT",
            "notNull": true
          },
          {
            "fieldPath": "iconUrl",
            "columnName": "iconUrl",
            "affinity": "TEXT",
            "notNull": true
          },
          {
            "fieldPath": "isSystemApp",
            "columnName": "isSystemApp",
            "affinity": "INTEGER",
            "notNull": true
          },
          {
            "fieldPath": "isInstalled",
            "columnName": "isInstalled",
            "affinity": "INTEGER",
            "notNull": true
          },
          {
            "fieldPath": "installTime",
            "columnName": "installTime",
            "affinity": "INTEGER",
            "notNull": true
          },
          {
            "fieldPath": "lastUpdated",
            "columnName": "lastUpdated",
            "affinity": "INTEGER",
            "notNull": true
          },
          {
            "fieldPath": "customNotes",
            "columnName": "customNotes",
            "affinity": "TEXT",
            "notNull": true
          },
          {
            "fieldPath": "usageCount",
            "columnName": "usageCount",
            "affinity": "INTEGER",
            "notNull": true
          },
          {
            "fieldPath": "lastUsedTimestamp",
            "columnName": "lastUsedTimestamp",
            "affinity": "INTEGER",
            "notNull": true
          },
          {
            "fieldPath": "notificationCount",
            "columnName": "notificationCount",
            "affinity": "INTEGER",
            "notNull": true
          },
          {
            "fieldPath": "notificationImportance",
            "columnName": "notificationImportance",
            "affinity": "INTEGER",
            "notNull": true
          },
          {
            "fieldPath": "notificationText",
            "columnName": "notificationText",
            "affinity": "TEXT",
            "notNull": true
          },
          {
            "fieldPath": "appSizeBytes",
            "columnName": "appSizeBytes",
            "affinity": "INTEGER",
            "notNull": true
          },
          {
            "fieldPath": "isHidden",
            "columnName": "isHidden",
            "affinity": "INTEGER",
            "notNull": true
          },
          {
            "fieldPath": "firstInstalledTime",
            "columnName": "firstInstalledTime",
            "affinity": "INTEGER",
            "notNull": true
          },
          {
            "fieldPath": "lastUpdatedTime",
            "columnName": "lastUpdatedTime",
            "affinity": "INTEGER",
            "notNull": true
          },
          {
            "fieldPath": "targetSdkVersion",
            "columnName": "targetSdkVersion",
            "affinity": "INTEGER",
            "notNull": true
          },
          {
            "fieldPath": "versionName",
            "columnName": "versionName",
            "affinity": "TEXT",
            "notNull": true
          }
        ],
        "primaryKey": {
          "autoGenerate": false,
          "columnNames": [
            "packageName"
          ]
        },
        "indices": [],
        "foreignKeys": []
      },
      {
        "tableName": "categories",
        "createSql": "CREATE TABLE IF NOT EXISTS `${TABLE_NAME}` (`categoryId` TEXT NOT NULL, `categoryName` TEXT NOT NULL, `description` TEXT NOT NULL, `colorHex` TEXT NOT NULL, `iconEmoji` TEXT NOT NULL, `isSystemCategory` INTEGER NOT NULL, `displayOrder` INTEGER NOT NULL, `createdAt` INTEGER NOT NULL, PRIMARY KEY(`categoryId`))",
        "fields": [
          {
            "fieldPath": "categoryId",
            "columnName": "categoryId",
            "affinity": "TEXT",
            "notNull": true
          },
          {
            "fieldPath": "categoryName",
            "columnName": "categoryName",
            "affinity": "TEXT",
            "notNull": true
          },
          {
            "fieldPath": "description",
            "columnName": "description",
            "affinity": "TEXT",
            "notNull": true
          },
          {
            "fieldPath": "colorHex",
            "columnName": "colorHex",
            "affinity": "TEXT",
            "notNull": true
          },
          {
            "fieldPath": "iconEmoji",
            "columnName": "iconEmoji",
            "affinity": "TEXT",
            "notNull": true
          },
          {
            "fieldPath": "isSystemCategory",
            "columnName": "isSystemCategory",
            "affinity": "INTEGER",
            "notNull": true
          },
          {
            "fieldPath": "displayOrder",
            "columnName": "displayOrder",
            "affinity": "INTEGER",
            "notNull": true
          },
          {
            "fieldPath": "createdAt",
            "columnName": "createdAt",
            "affinity": "INTEGER",
            "notNull": true
          }
        ],
        "primaryKey": {
          "autoGenerate": false,
          "columnNames": [
            "categoryId"
          ]
        },
        "indices": [],
        "foreignKeys": []
      }
    ],
    "views": [],
    "setupQueries": [
      "CREATE TABLE IF NOT EXISTS room_master_table (id INTEGER PRIMARY KEY,identity_hash TEXT)",
      "INSERT OR REPLACE INTO room_master_table (id,identity_hash) VALUES(42, 'c77197d0c2a39d8d1595fc3bbf9d8368')"
    ]
  }
}